arsenix/__init__.py
arsenix/algorithm/__init__.py
arsenix/algorithm/fyp.py
arsenix/cache/__init__.py
arsenix/cache/disk.py
arsenix/cache/local.py
arsenix/cache/redis_cache.py
arsenix/pattern/__init__.py
arsenix/pattern/learner.py
arsenix/presets/__init__.py
arsenix/presets/fyp.py
arsenix/server/__init__.py
arsenix/server/main.py
arsenix/setup/__init__.py
arsenix/setup/getter.py
arsenix/setup/setter.py
arsenix-0.1.0.dist-info/licenses/LICENSE
arsenix-0.1.0.dist-info/METADATA
arsenix-0.1.0.dist-info/WHEEL
arsenix-0.1.0.dist-info/top_level.txt
arsenix-0.1.0.dist-info/RECORD
