Metadata-Version: 2.4
Name: arsenix
Version: 0.1.0
Summary: A lightweight, minimalist, fast caching and pattern design library.
Project-URL: Homepage, https://github.com/mebaadwaheed/arsenix
Project-URL: Bug Tracker, https://github.com/mebaadwaheed/arsenix/issues
Classifier: Programming Language :: Python :: 3
Classifier: License :: OSI Approved :: MIT License
Classifier: Operating System :: OS Independent
Requires-Python: >=3.8
License-File: LICENSE
Requires-Dist: PyYAML>=6.0
Requires-Dist: aiofiles>=23.1.0
Provides-Extra: diskcache
Requires-Dist: diskcache>=5.4.0; extra == "diskcache"
Provides-Extra: redis
Requires-Dist: redis>=4.3.4; extra == "redis"
Dynamic: license-file
